{
  "project_info": {
    "project_number": "604710483383",
    "firebase_url": "https://messenger.firebaseio.com",
    "project_id": "chatapps-7e01d",
    "storage_bucket": "chatapps-7e01d.appspot.com"
  },
  "client": [
    {
      "client_info": {
        "mobilesdk_app_id": "1:604710483383:android:698de8a1a1bbaf3263e432",
        "android_client_info": {
          "package_name": "org.chatapps.messenger"
        }
      },
      "oauth_client": [
        {
          "client_id": "604710483383-c5f32ccs26q6j3ikbesj1rs5slrebger.apps.googleusercontent.com",
          "client_type": 3
        }
      ],
      "api_key": [
        {
          "current_key": "AIzaSyCgGyPvCUWJd0kYeq5LPLjy9oFdCoAq3uU"
        }
      ],
      "services": {
        "appinvite_service": {
          "other_platform_oauth_client": [
            {
              "client_id": "604710483383-c5f32ccs26q6j3ikbesj1rs5slrebger.apps.googleusercontent.com",
              "client_type": 3
            }
          ]
        }
      }
    },
    {
      "client_info": {
        "mobilesdk_app_id": "1:604710483383:android:033fe9567acb4e6963e432",
        "android_client_info": {
          "package_name": "org.chatapps.messenger"
        }
      },
      "oauth_client": [
        {
          "client_id": "604710483383-c5f32ccs26q6j3ikbesj1rs5slrebger.apps.googleusercontent.com",
          "client_type": 3
        }
      ],
      "api_key": [
        {
          "current_key": "AIzaSyCgGyPvCUWJd0kYeq5LPLjy9oFdCoAq3uU"
        }
      ],
      "services": {
        "appinvite_service": {
          "other_platform_oauth_client": [
            {
              "client_id": "604710483383-c5f32ccs26q6j3ikbesj1rs5slrebger.apps.googleusercontent.com",
              "client_type": 3
            }
          ]
        }
      }
    }
  ],
  "configuration_version": "1"
}